llama_index/py.typed
llama_index/vector_stores/vertexaivectorsearch/__init__.py
llama_index/vector_stores/vertexaivectorsearch/_sdk_manager.py
llama_index/vector_stores/vertexaivectorsearch/_v2_operations.py
llama_index/vector_stores/vertexaivectorsearch/base.py
llama_index/vector_stores/vertexaivectorsearch/utils.py
llama_index_vector_stores_vertexaivectorsearch-0.3.4.dist-info/METADATA
llama_index_vector_stores_vertexaivectorsearch-0.3.4.dist-info/WHEEL
llama_index_vector_stores_vertexaivectorsearch-0.3.4.dist-info/licenses/LICENSE
llama_index_vector_stores_vertexaivectorsearch-0.3.4.dist-info/RECORD
