Metadata-Version: 2.4
Name: llama-index-vector-stores-vertexaivectorsearch
Version: 0.3.4
Summary: llama-index vector_stores Vertex AI Vector Search integration
Author-email: Your Name <you@example.com>
License-Expression: MIT
License-File: LICENSE
Requires-Python: <4.0,>=3.9
Requires-Dist: google-cloud-aiplatform<2,>=1.39.0
Requires-Dist: google-cloud-storage<3,>=2.16.0
Requires-Dist: llama-index-core<0.15,>=0.13.0
Requires-Dist: llama-index-embeddings-vertex<0.5,>=0.4.0
Provides-Extra: v2
Requires-Dist: google-cloud-vectorsearch>=0.1.0; extra == 'v2'
